reverseAbliterator/__init__.py
reverseAbliterator/reverseAbliterator.py
reverseAbliterator/utils.py
reverseAbliterator-0.1.0.dist-info/LICENSE
reverseAbliterator-0.1.0.dist-info/METADATA
reverseAbliterator-0.1.0.dist-info/WHEEL
reverseAbliterator-0.1.0.dist-info/top_level.txt
reverseAbliterator-0.1.0.dist-info/RECORD
