Metadata-Version: 2.1
Name: reverseAbliterator
Version: 0.1.0
Summary: A package for reverse ablitation of language models
Author-email: Leo Borcherding <borchink@gmail.com>
Project-URL: Homepage, https://github.com/leoleojames1/reverseAbliterator
Project-URL: Bug Tracker, https://github.com/leoleojames1/reverseAbliterator/issues
Project-URL: Source, https://github.com/leoleojames1/reverseAbliterator
Classifier: Programming Language :: Python :: 3
Classifier: License :: OSI Approved :: Apache Software License
Classifier: Operating System :: OS Independent
Classifier: Development Status :: 3 - Alpha
Classifier: Intended Audience :: Developers
Classifier: Topic :: Software Development :: Libraries :: Python Modules
Requires-Python: >=3.7
License-File: LICENSE
Requires-Dist: torch
Requires-Dist: einops
Requires-Dist: tqdm
Requires-Dist: transformer-lens
Requires-Dist: jaxtyping
Requires-Dist: scikit-learn
